vespy/__init__.py
vespy/certificates/Vestas Issuing CA 01 G1.crt
vespy/certificates/Vestas Issuing CA 02 G1.crt
vespy/certificates/Vestas Issuing CA 03 G1.crt
vespy/certificates/Vestas Root CA 01 G1.crt
vespy/certificates/vestas-web-gateway-cert.crt
vespy/main.py
vespy/ssl_utils.py
vespy-0.0.20rc3.dist-info/entry_points.txt
vespy-0.0.20rc3.dist-info/WHEEL
vespy-0.0.20rc3.dist-info/METADATA
vespy-0.0.20rc3.dist-info/RECORD
